CalcSeb/__init__.py
CalcSeb/__main__.py
CalcSeb/coolstuff.py
CalcSeb/main.py
CalcSeb/areas/IrrAreas.py
CalcSeb/areas/areas.py
CalcSeb/areas/areas2D.py
CalcSeb/areas/areas3D.py
CalcSeb/areas/test_irr_polygon.py
CalcSeb/arithmetic/arithmetic.py
CalcSeb/graphics/graph.py
CalcSeb/special_functions/special-functions.py
CalcSeb/trigonometry/trig.py
calcseb-0.1.0.dist-info/licenses/LICENSE
calcseb-0.1.0.dist-info/METADATA
calcseb-0.1.0.dist-info/WHEEL
calcseb-0.1.0.dist-info/top_level.txt
calcseb-0.1.0.dist-info/RECORD
