Metadata-Version: 2.4
Name: CalcSeb
Version: 0.1.0
Summary: La colaboración más loca y chévere que jamás se ha hecho
Author-email: Sebastian Rodriguez Garcia <sebrodriguezg@udistrital.edu.co>
License: Copyright (c) 2025 Sebastian Rodriguez Garcia  
Project-URL: Homepage, https://github.com/configurarpc/calculadora
Requires-Python: >=3.8
License-File: LICENSE
Requires-Dist: numpy
Requires-Dist: matplotlib
Requires-Dist: seaborn
Requires-Dist: plotly
Dynamic: license-file
